pytest_mqtt/__init__.py
pytest_mqtt/capmqtt.py
pytest_mqtt/model.py
pytest_mqtt/mosquitto.py
pytest_mqtt/py.typed
pytest_mqtt/util.py
pytest_mqtt-0.6.2.dist-info/licenses/LICENSE
pytest_mqtt-0.6.2.dist-info/METADATA
pytest_mqtt-0.6.2.dist-info/WHEEL
pytest_mqtt-0.6.2.dist-info/entry_points.txt
pytest_mqtt-0.6.2.dist-info/top_level.txt
pytest_mqtt-0.6.2.dist-info/RECORD
