Metadata-Version: 2.4
Name: pytest-mqtt
Version: 0.6.2
Summary: pytest-mqtt supports testing systems based on MQTT
Author-email: Andreas Motl <andreas.motl@panodata.org>, Richard Pobering <richard.pobering@panodata.org>
Project-URL: changelog, https://github.com/mqtt-tools/pytest-mqtt/blob/main/CHANGES.rst
Project-URL: documentation, https://github.com/mqtt-tools/pytest-mqtt
Project-URL: homepage, https://github.com/mqtt-tools/pytest-mqtt
Project-URL: repository, https://github.com/mqtt-tools/pytest-mqtt
Keywords: mosquitto,mqtt,paho,pytest,testing
Classifier: Development Status :: 5 - Production/Stable
Classifier: Environment :: Console
Classifier: Framework :: Pytest
Classifier: Intended Audience :: Customer Service
Classifier: Intended Audience :: Developers
Classifier: Intended Audience :: Education
Classifier: Intended Audience :: Information Technology
Classifier: Intended Audience :: Legal Industry
Classifier: Intended Audience :: Manufacturing
Classifier: Intended Audience :: System Administrators
Classifier: Intended Audience :: Telecommunications Industry
Classifier: Operating System :: MacOS :: MacOS X
Classifier: Operating System :: POSIX :: Linux
Classifier: Operating System :: Unix
Classifier: Programming Language :: Python
Classifier: Programming Language :: Python :: 3 :: Only
Classifier: Programming Language :: Python :: 3.7
Classifier: Programming Language :: Python :: 3.8
Classifier: Programming Language :: Python :: 3.9
Classifier: Programming Language :: Python :: 3.10
Classifier: Programming Language :: Python :: 3.11
Classifier: Programming Language :: Python :: 3.12
Classifier: Programming Language :: Python :: 3.13
Classifier: Programming Language :: Python :: 3.14
Classifier: Topic :: Communications
Classifier: Topic :: Education
Classifier: Topic :: Home Automation
Classifier: Topic :: Software Development :: Libraries
Classifier: Topic :: Software Development :: Object Brokering
Classifier: Topic :: System :: Hardware
Classifier: Topic :: System :: Logging
Classifier: Topic :: System :: Monitoring
Classifier: Topic :: System :: Networking
Classifier: Topic :: System :: Networking :: Monitoring
Classifier: Topic :: System :: Systems Administration
Classifier: Topic :: Utilities
Requires-Python: >=3.7
License-File: LICENSE
Requires-Dist: dataclasses; python_version < "3.7"
Requires-Dist: importlib-metadata; python_version < "3.8"
Requires-Dist: paho-mqtt<3
Requires-Dist: pytest-docker-fixtures<2
Provides-Extra: develop
Requires-Dist: mypy<1.20; extra == "develop"
Requires-Dist: poethepoet<1; extra == "develop"
Requires-Dist: pyproject-fmt<3; extra == "develop"
Requires-Dist: ruff<0.15; extra == "develop"
Requires-Dist: validate-pyproject<1; extra == "develop"
Provides-Extra: release
Requires-Dist: build<2; extra == "release"
Requires-Dist: twine<7; extra == "release"
Provides-Extra: test
Requires-Dist: coverage<8; extra == "test"
Requires-Dist: pytest<9; extra == "test"
Requires-Dist: pytest-fixture-order<1; extra == "test"
Requires-Dist: pytest-httpserver<2; extra == "test"
Requires-Dist: pytest-ordering<1; extra == "test"
Dynamic: license-file
